{
  "String1": "Libero di giocare",
  "String2": "Questo gioco è gratuito, ciò significa che può essere giocato gratuitamente, ma per goderne appieno che sarà necessario acquistare uno o più download di contenuti (o DLC in breve).",
  "String3": "Contenuto sessuale",
  "String4": "Questo gioco contiene contenuti sessuali non adatti ai minori.",
  "String5": "Questo DLC contiene contenuti sessuali non adatti ai minori.",
  "String6": "Per visualizzare il contenuto, è necessario registrare un account sul sito Web.",
  "String7": "Intelligenza artificiale",
  "String8": "Questo gioco ha utilizzato l'intelligenza artificiale nel suo sviluppo. ",
  "String9": "Abbandonato",
  "String10": "Questo gioco di accesso precoce è stato abbandonato dallo sviluppatore in quanto non è stato aggiornato per {0}.",
  "String11": "Accesso precoce",
  "String12": "Questo gioco è in anticipo, il che significa che è ancora in fase di sviluppo e mancheranno le caratteristiche.",
  "String13": "Realtà virtuale",
  "String14": "Questo gioco può essere eseguito solo con un dispositivo di realtà virtuale.",
  "String15": "DLC",
  "String16": "Questo è un DLC e richiede che il gioco {0} funzioni correttamente (fai clic sul pulsante per aprirlo).",
  "String17": "Colonna sonora",
  "String18": "È una colonna sonora di videogiochi, ciò significa che avrai accesso solo ai file audio del gioco.",
  "String19": "Demo",
  "String20": "Una demo del gioco è disponibile su Steam (fai clic sul pulsante per aprirlo)."
}